[
  {"id":1,"title":"深入理解计算机系统","author":"Randal E. Bryant","category":"编程技术","rating":9.8},
  {"id":2,"title":"代码大全","author":"Steve McConnell","category":"编程技术","rating":9.5},
  {"id":3,"title":"算法导论","author":"Thomas H. Cormen","category":"编程技术","rating":9.7},
  {"id":4,"title":"Python编程：从入门到实践","author":"Eric Matthes","category":"编程技术","rating":9.2},
  {"id":5,"title":"设计模式","author":"Erich Gamma","category":"编程技术","rating":9.4},
  {"id":6,"title":"数据结构与算法分析","author":"Mark Allen Weiss","category":"编程技术","rating":9.1},
  {"id":7,"title":"Clean Code：代码整洁之道","author":"Robert C. Martin","category":"编程技术","rating":9.3},
  {"id":8,"title":"数据库系统概念","author":"Abraham Silberschatz","category":"编程技术","rating":9.0},
  {"id":9,"title":"TCP/IP详解","author":"W. Richard Stevens","category":"编程技术","rating":9.6},
  {"id":10,"title":"流畅的Python","author":"Luciano Ramalho","category":"编程技术","rating":9.3},
  {"id":11,"title":"重构：改善既有代码的设计","author":"Martin Fowler","category":"编程技术","rating":9.2},
  {"id":12,"title":"程序员修炼之道","author":"Andrew Hunt","category":"编程技术","rating":9.1},
  {"id":13,"title":"编译原理","author":"Alfred V. Aho","category":"编程技术","rating":9.5},
  {"id":14,"title":"操作系统概念","author":"Abraham Silberschatz","category":"编程技术","rating":9.0},
  {"id":15,"title":"计算机网络：自顶向下方法","author":"James F. Kurose","category":"编程技术","rating":9.2},
  {"id":16,"title":"JavaScript高级程序设计","author":"Matt Frisbie","category":"编程技术","rating":9.1},
  {"id":17,"title":"C++ Primer Plus","author":"Stephen Prata","category":"编程技术","rating":9.3},
  {"id":18,"title":"Go程序设计语言","author":"Alan Donovan","category":"编程技术","rating":9.0},
  {"id":19,"title":"Rust程序设计","author":"Steve Klabnik","category":"编程技术","rating":8.9},
  {"id":20,"title":"黑客与画家","author":"Paul Graham","category":"编程技术","rating":9.1},
  {"id":21,"title":"人月神话","author":"Frederick Brooks","category":"编程技术","rating":8.8},
  {"id":22,"title":"编程珠玑","author":"Jon Bentley","category":"编程技术","rating":9.2},
  {"id":23,"title":"Effective Java","author":"Joshua Bloch","category":"编程技术","rating":9.3},
  {"id":24,"title":"深入理解Java虚拟机","author":"周志明","category":"编程技术","rating":9.4},
  {"id":25,"title":"Spring实战","author":"Craig Walls","category":"编程技术","rating":8.7},
  {"id":26,"title":"高性能MySQL","author":"Baron Schwartz","category":"编程技术","rating":9.1},
  {"id":27,"title":"Redis设计与实现","author":"黄健宏","category":"编程技术","rating":9.2},
  {"id":28,"title":"Docker从入门到实践","author":"杨保华","category":"编程技术","rating":8.8},
  {"id":29,"title":"Kubernetes权威指南","author":"龚正","category":"编程技术","rating":8.9},
  {"id":30,"title":"人工智能：一种现代方法","author":"Stuart Russell","category":"人工智能","rating":9.7},
  {"id":31,"title":"机器学习","author":"周志华","category":"人工智能","rating":9.6},
  {"id":32,"title":"深度学习","author":"Ian Goodfellow","category":"人工智能","rating":9.5},
  {"id":33,"title":"统计学习方法","author":"李航","category":"人工智能","rating":9.4},
  {"id":34,"title":"动手学深度学习","author":"阿斯顿·张","category":"人工智能","rating":9.3},
  {"id":35,"title":"机器学习实战","author":"Peter Harrington","category":"人工智能","rating":8.9},
  {"id":36,"title":"Python机器学习","author":"Sebastian Raschka","category":"人工智能","rating":9.1},
  {"id":37,"title":"强化学习导论","author":"Richard S. Sutton","category":"人工智能","rating":9.6},
  {"id":38,"title":"模式识别与机器学习","author":"Christopher Bishop","category":"人工智能","rating":9.4},
  {"id":39,"title":"计算机视觉：算法与应用","author":"Richard Szeliski","category":"人工智能","rating":8.8},
  {"id":40,"title":"自然语言处理综论","author":"Daniel Jurafsky","category":"人工智能","rating":9.0},
  {"id":41,"title":"数据挖掘导论","author":"Pang-Ning Tan","category":"人工智能","rating":8.9},
  {"id":42,"title":"推荐系统实践","author":"项亮","category":"人工智能","rating":8.7},
  {"id":43,"title":"三体","author":"刘慈欣","category":"文学","rating":9.8},
  {"id":44,"title":"三体Ⅱ：黑暗森林","author":"刘慈欣","category":"文学","rating":9.7},
  {"id":45,"title":"三体Ⅲ：死神永生","author":"刘慈欣","category":"文学","rating":9.6},
  {"id":46,"title":"红楼梦","author":"曹雪芹","category":"文学","rating":9.9},
  {"id":47,"title":"活着","author":"余华","category":"文学","rating":9.7},
  {"id":48,"title":"百年孤独","author":"马尔克斯","category":"文学","rating":9.6},
  {"id":49,"title":"1984","author":"George Orwell","category":"文学","rating":9.5},
  {"id":50,"title":"围城","author":"钱钟书","category":"文学","rating":9.3},
  {"id":51,"title":"平凡的世界","author":"路遥","category":"文学","rating":9.6},
  {"id":52,"title":"许三观卖血记","author":"余华","category":"文学","rating":9.2},
  {"id":53,"title":"白鹿原","author":"陈忠实","category":"文学","rating":9.4},
  {"id":54,"title":"黄金时代","author":"王小波","category":"文学","rating":9.1},
  {"id":55,"title":"沉默的大多数","author":"王小波","category":"文学","rating":9.3},
  {"id":56,"title":"挪威的森林","author":"村上春树","category":"文学","rating":8.9},
  {"id":57,"title":"哈利·波特与魔法石","author":"J.K. Rowling","category":"文学","rating":9.3},
  {"id":58,"title":"指环王：魔戒再现","author":"J.R.R. Tolkien","category":"文学","rating":9.5},
  {"id":59,"title":"小王子","author":"Antoine de Saint-Exupéry","category":"文学","rating":9.4},
  {"id":60,"title":"追风筝的人","author":"Khaled Hosseini","category":"文学","rating":9.3},
  {"id":61,"title":"杀死一只知更鸟","author":"Harper Lee","category":"文学","rating":9.5},
  {"id":62,"title":"飘","author":"Margaret Mitchell","category":"文学","rating":9.4},
  {"id":63,"title":"百年孤独","author":"加西亚·马尔克斯","category":"文学","rating":9.6},
  {"id":64,"title":"人类简史","author":"Yuval Noah Harari","category":"人文社科","rating":9.5},
  {"id":65,"title":"未来简史","author":"Yuval Noah Harari","category":"人文社科","rating":9.2},
  {"id":66,"title":"枪炮、病菌与钢铁","author":"Jared Diamond","category":"人文社科","rating":9.4},
  {"id":67,"title":"社会心理学","author":"David Myers","category":"人文社科","rating":9.3},
  {"id":68,"title":"影响力","author":"Robert Cialdini","category":"人文社科","rating":9.1},
  {"id":69,"title":"乌合之众","author":"Gustave Le Bon","category":"人文社科","rating":8.9},
  {"id":70,"title":"自卑与超越","author":"Alfred Adler","category":"人文社科","rating":9.0},
  {"id":71,"title":"娱乐至死","author":"Neil Postman","category":"人文社科","rating":8.8},
  {"id":72,"title":"乡土中国","author":"费孝通","category":"人文社科","rating":9.3},
  {"id":73,"title":"时间简史","author":"Stephen Hawking","category":"自然科学","rating":9.5},
  {"id":74,"title":"上帝掷骰子吗","author":"曹天元","category":"自然科学","rating":9.4},
  {"id":75,"title":"自私的基因","author":"Richard Dawkins","category":"自然科学","rating":9.3},
  {"id":76,"title":"万物简史","author":"Bill Bryson","category":"自然科学","rating":9.1},
  {"id":77,"title":"双螺旋","author":"James Watson","category":"自然科学","rating":8.7},
  {"id":78,"title":"奇点临近","author":"Ray Kurzweil","category":"自然科学","rating":8.6},
  {"id":79,"title":"国富论","author":"Adam Smith","category":"经济管理","rating":9.4},
  {"id":80,"title":"经济学原理：微观经济学","author":"N. Gregory Mankiw","category":"经济管理","rating":9.5},
  {"id":81,"title":"经济学原理：宏观经济学","author":"N. Gregory Mankiw","category":"经济管理","rating":9.4},
  {"id":82,"title":"穷查理宝典","author":"Charlie Munger","category":"经济管理","rating":9.3},
  {"id":83,"title":"从0到1","author":"Peter Thiel","category":"经济管理","rating":8.8},
  {"id":84,"title":"思考，快与慢","author":"Daniel Kahneman","category":"经济管理","rating":9.2},
  {"id":85,"title":"创新者的窘境","author":"Clayton Christensen","category":"经济管理","rating":9.0},
  {"id":86,"title":"高效能人士的七个习惯","author":"Stephen R. Covey","category":"经济管理","rating":9.1},
  {"id":87,"title":"精益创业","author":"Eric Ries","category":"经济管理","rating":8.9},
  {"id":88,"title":"竞争战略","author":"Michael Porter","category":"经济管理","rating":9.0},
  {"id":89,"title":"道德经","author":"老子","category":"哲学","rating":9.8},
  {"id":90,"title":"论语","author":"孔子","category":"哲学","rating":9.7},
  {"id":91,"title":"庄子","author":"庄子","category":"哲学","rating":9.5},
  {"id":92,"title":"孟子","author":"孟子","category":"哲学","rating":9.3},
  {"id":93,"title":"纯粹理性批判","author":"Immanuel Kant","category":"哲学","rating":9.5},
  {"id":94,"title":"存在与时间","author":"Martin Heidegger","category":"哲学","rating":9.3},
  {"id":95,"title":"苏菲的世界","author":"Jostein Gaarder","category":"哲学","rating":9.2},
  {"id":96,"title":"人生的智慧","author":"叔本华","category":"哲学","rating":9.1},
  {"id":97,"title":"尼采：在世纪的转折点上","author":"周国平","category":"哲学","rating":8.9},
  {"id":98,"title":"中国哲学简史","author":"冯友兰","category":"哲学","rating":9.4},
  {"id":99,"title":"明朝那些事儿","author":"当年明月","category":"历史","rating":9.4},
  {"id":100,"title":"万历十五年","author":"黄仁宇","category":"历史","rating":9.3},
  {"id":101,"title":"全球通史","author":"L.S. Stavrianos","category":"历史","rating":9.5},
  {"id":102,"title":"中国通史","author":"吕思勉","category":"历史","rating":9.4},
  {"id":103,"title":"历史的教训","author":"Will Durant","category":"历史","rating":9.0},
  {"id":104,"title":"人类群星闪耀时","author":"Stefan Zweig","category":"历史","rating":9.1},
  {"id":105,"title":"被讨厌的勇气","author":"岸见一郎","category":"心理自助","rating":9.2},
  {"id":106,"title":"心流","author":"Mihaly Csikszentmihalyi","category":"心理自助","rating":9.0},
  {"id":107,"title":"习惯的力量","author":"Charles Duhigg","category":"心理自助","rating":8.9},
  {"id":108,"title":"刻意练习","author":"Anders Ericsson","category":"心理自助","rating":9.1},
  {"id":109,"title":"自控力","author":"Kelly McGonigal","category":"心理自助","rating":8.8},
  {"id":110,"title":"情商","author":"Daniel Goleman","category":"心理自助","rating":8.9},
  {"id":111,"title":"思考的力量","author":"Richard Paul","category":"心理自助","rating":8.6},
  {"id":112,"title":"简约至上","author":"Giles Colborne","category":"设计","rating":9.0},
  {"id":113,"title":"点石成金","author":"Steve Krug","category":"设计","rating":9.1},
  {"id":114,"title":"设计心理学","author":"Donald Norman","category":"设计","rating":9.2},
  {"id":115,"title":"写给大家看的设计书","author":"Robin Williams","category":"设计","rating":9.0},
  {"id":116,"title":"Don't Make Me Think","author":"Steve Krug","category":"设计","rating":9.3},
  {"id":117,"title":"About Face 3交互设计精髓","author":"Alan Cooper","category":"设计","rating":8.8},
  {"id":118,"title":"用户体验要素","author":"Jesse James Garrett","category":"设计","rating":8.9},
  {"id":119,"title":"梦的解析","author":"Sigmund Freud","category":"心理自助","rating":8.7},
  {"id":120,"title":"超越自卑","author":"Alfred Adler","category":"心理自助","rating":8.8}
]